LICENSE
README.md
setup.py
pi_brightness/__init__.py
pi_brightness/pi_brightness.py
pi_brightness.egg-info/PKG-INFO
pi_brightness.egg-info/SOURCES.txt
pi_brightness.egg-info/dependency_links.txt
pi_brightness.egg-info/top_level.txt