Metadata-Version: 2.1
Name: pi-brightness
Version: 1.0.2
Summary: Controls Raspberry Pi screen brightness (or other Linux devices)
Author: Joseph McMahon
License-File: LICENSE
